reactea/__init__.py
reactea/cli.py
reactea/constants.py
reactea/case_studies/__init__.py
reactea/case_studies/case_study.py
reactea/case_studies/compound_quality.py
reactea/case_studies/sweeteners.py
reactea/chem/__init__.py
reactea/chem/chem_utils.py
reactea/chem/compounds.py
reactea/chem/reaction_rules.py
reactea/chem/standardization.py
reactea/data/reactionrules/reaction_rules_reactea.tsv.bz2
reactea/io_streams/__init__.py
reactea/io_streams/readers.py
reactea/io_streams/writers.py
reactea/optimization/__init__.py
reactea/optimization/comparators.py
reactea/optimization/ea.py
reactea/optimization/evaluation.py
reactea/optimization/problem.py
reactea/optimization/solution.py
reactea/optimization/jmetal/__init__.py
reactea/optimization/jmetal/algorithms.py
reactea/optimization/jmetal/ea.py
reactea/optimization/jmetal/evaluators.py
reactea/optimization/jmetal/generators.py
reactea/optimization/jmetal/observers.py
reactea/optimization/jmetal/operators.py
reactea/optimization/jmetal/problem.py
reactea/optimization/jmetal/terminators.py
reactea/vizualization/__init__.py
reactea/vizualization/plot_results.py
reactea/wrappers/__init__.py
reactea/wrappers/wrap_case_study.py
reactea/wrappers/wrap_evaluation_function.py
reactea-1.0.0.dist-info/LICENSE
reactea-1.0.0.dist-info/METADATA
reactea-1.0.0.dist-info/WHEEL
reactea-1.0.0.dist-info/entry_points.txt
reactea-1.0.0.dist-info/top_level.txt
reactea-1.0.0.dist-info/RECORD
