Metadata-Version: 2.2
Name: reactea
Version: 1.0.0
Summary: ReactEA: Combining Evolutionary Algorithms with Reaction Rules Towards Focused Molecular Design
Home-page: https://github.com/BioSystemsUM/ReactEA
Author: João Correia
Author-email: jfscorreia95@gmail.com
License: GPL-3.0 license
Keywords: evolutionary-algorithms,drug-discovery,reaction-rules
Platform: unix
Platform: linux
Platform: osx
Platform: cygwin
Platform: win32
Classifier: Development Status :: 5 - Production/Stable
Classifier: License :: OSI Approved :: MIT License
Classifier: Programming Language :: Python :: 3.7
Classifier: Programming Language :: Python :: 3.8
Requires-Python: >=3.7
License-File: LICENSE
Requires-Dist: rdkit-pypi==2022.03.1
Requires-Dist: numpy==1.21.5
Requires-Dist: pandas==1.3.5
Requires-Dist: cytoolz==0.11.2
Requires-Dist: jmetalpy
Requires-Dist: PyYAML==6.0
Requires-Dist: matplotlib==3.5.1
Requires-Dist: chembl_structure_pipeline
Requires-Dist: joblib==1.1.0
Requires-Dist: networkx==2.6.3
Requires-Dist: click==8.1.3
Provides-Extra: testing
Requires-Dist: pytest>=7.1.1; extra == "testing"
Requires-Dist: pytest-cov>=3.0.0; extra == "testing"
Requires-Dist: mypy>=0.942; extra == "testing"
Requires-Dist: flake8>=4.0.1; extra == "testing"
Requires-Dist: tox>=3.25.0; extra == "testing"
